dico_extsource/AudioFifo.py
dico_extsource/AudioFilter.py
dico_extsource/AudioVisualizerTransfer.py
dico_extsource/CrossfadePlayer.py
dico_extsource/FadedVolumeTransfer.py
dico_extsource/GaplessPlayer.py
dico_extsource/Lyrics.py
dico_extsource/PyAVSource.py
dico_extsource/VideoSource.py
dico_extsource/YTDLSource.py
dico_extsource/YTDLVideoSource.py
dico_extsource/__init__.py
dico_extsource/exceptions.py
dico_extsource/extractor.py
dico_extsource/mixer.py
dico_extsource/utils/__init__.py
dico_extsource/utils/threadLock.py
dico_extsource-0.0.4.dist-info/LICENSE
dico_extsource-0.0.4.dist-info/METADATA
dico_extsource-0.0.4.dist-info/WHEEL
dico_extsource-0.0.4.dist-info/top_level.txt
dico_extsource-0.0.4.dist-info/RECORD
