Metadata-Version: 2.1
Name: dico-extsource
Version: 0.0.4
Summary: Enhanced Audio Source for dico.
Home-page: https://github.com/eunwoo1104/dico-extsource
Author: eunwoo1104
Author-email: sions04@naver.com
License: UNKNOWN
Platform: UNKNOWN
Classifier: Programming Language :: Python :: 3
Requires-Python: >=3.7
License-File: LICENSE
Requires-Dist: av
Requires-Dist: yt-dlp
Requires-Dist: markdownify
Requires-Dist: numpy
